TextSimilarScore/__init__.py
TextSimilarScore/tools/TextSim.py
TextSimilarScore/tools/__init__.py
TextSimilarScore-0.0.6.dist-info/LICENSE
TextSimilarScore-0.0.6.dist-info/METADATA
TextSimilarScore-0.0.6.dist-info/WHEEL
TextSimilarScore-0.0.6.dist-info/top_level.txt
TextSimilarScore-0.0.6.dist-info/RECORD
