Metadata-Version: 2.1
Name: TextSimilarScore
Version: 0.0.6
Summary: compute similar scores of two text
Home-page: https://github.com/shawshany/TextSimilarScore
Author: Ora
Author-email: victor.xsyang@gmail.com
License: UNKNOWN
Platform: UNKNOWN
Classifier: Programming Language :: Python :: 3
Classifier: License :: OSI Approved :: MIT License
Classifier: Operating System :: OS Independent
Requires-Python: >=3.*
